{
    "id": "atwine/Llama-2-7b-chat-q8-gguf",
    "status": "init",
    "model_type": "unknown",
    "name": "",
    "summary": "",
    "author": {
        "name": "atwine",
        "url": "",
        "description": ""
    },
    "size": "",
    "requires": "",
    "released_at": "2023-09-22T11:02:10Z",
    "architecture": "",
    "files": [
        {
            "name": "Llama-2-7b-chat-q8.gguf",
            "size": "7161089728",
            "quantization": "",
            "tags": [],
            "sha256": "f8e05686878fcea6c5605e20d6d03220d8c5841eced84f2226e3cdcd3c78f6f0",
            "download": {
                "default": "https://huggingface.co/atwine/Llama-2-7b-chat-q8-gguf/resolve/main/Llama-2-7b-chat-q8.gguf"
            }
        }
    ],
    "prompt_template": "",
    "reverse_prompt": "",
    "context_size": 0,
    "vector_size": 0,
    "metrics": {}
}