{
    "id": "danielus/MermaidSolar-Q4_K_S-GGUF",
    "status": "init",
    "model_type": "unknown",
    "name": "",
    "summary": "",
    "author": {
        "name": "danielus",
        "url": "",
        "description": ""
    },
    "size": "",
    "requires": "",
    "released_at": "2024-04-03T10:34:38Z",
    "architecture": "",
    "files": [
        {
            "name": "mermaidsolar.Q4_K_S.gguf",
            "size": "6118520960",
            "quantization": "Q4_K_S",
            "tags": [],
            "sha256": "1ab8695ccff948c1d2e6e3db1f5f9992506bcfab9cc1dc20b03dfcad48b90373",
            "download": {
                "default": "https://huggingface.co/danielus/MermaidSolar-Q4_K_S-GGUF/resolve/main/mermaidsolar.Q4_K_S.gguf"
            }
        }
    ],
    "prompt_template": "",
    "reverse_prompt": "",
    "context_size": 0,
    "vector_size": 0,
    "metrics": null
}