{
    "id": "hrabalm/TowerInstruct-7B-v0.1-gguf",
    "status": "init",
    "model_type": "unknown",
    "name": "",
    "summary": "",
    "author": {
        "name": "hrabalm",
        "url": "",
        "description": ""
    },
    "size": "",
    "requires": "",
    "released_at": "2024-01-12T19:23:06Z",
    "architecture": "",
    "files": [
        {
            "name": "TowerInstruct-7B-v0.1_Q4_K.gguf",
            "size": "4081044608",
            "quantization": "Q4_K",
            "tags": [],
            "sha256": "4de7b9084ce3f8801163b6b60a79b6043479ebd32b87ca8b046324c6eb32d20c",
            "download": {
                "default": "https://huggingface.co/hrabalm/TowerInstruct-7B-v0.1-gguf/resolve/main/TowerInstruct-7B-v0.1_Q4_K.gguf"
            }
        }
    ],
    "prompt_template": "",
    "reverse_prompt": "",
    "context_size": 0,
    "vector_size": 0,
    "metrics": {}
}