{
    "id": "TheBloke/MythoMix-L2-13B-GGUF",
    "status": "init",
    "model_type": "unknown",
    "name": "",
    "summary": "",
    "author": {
        "name": "TheBloke",
        "url": "https://github.com/TheBloke",
        "description": ""
    },
    "size": "",
    "requires": "",
    "released_at": "2023-09-05T03:24:12Z",
    "architecture": "",
    "files": [
        {
            "name": "mythomix-l2-13b.Q2_K.gguf",
            "size": "5429348224",
            "quantization": "Q2_K",
            "tags": [],
            "sha256": "e728a14c6e1fe1df50dcf1bd8c91e6c51f000205be485ac16d7b1288e256abe1",
            "download": {
                "default": "https://huggingface.co/TheBloke/MythoMix-L2-13B-GGUF/resolve/main/mythomix-l2-13b.Q2_K.gguf"
            }
        },
        {
            "name": "mythomix-l2-13b.Q3_K_L.gguf",
            "size": "6929559424",
            "quantization": "Q3_K_L",
            "tags": [],
            "sha256": "30082d4e78af2ea0aaf028721e89ce779760d6d187ccce8b28add42824725904",
            "download": {
                "default": "https://huggingface.co/TheBloke/MythoMix-L2-13B-GGUF/resolve/main/mythomix-l2-13b.Q3_K_L.gguf"
            }
        },
        {
            "name": "mythomix-l2-13b.Q3_K_M.gguf",
            "size": "6337769344",
            "quantization": "Q3_K_M",
            "tags": [],
            "sha256": "5111b6020506c9d7546ce6ced65f1b6ff5ed62b800bca15460a573ac40c898af",
            "download": {
                "default": "https://huggingface.co/TheBloke/MythoMix-L2-13B-GGUF/resolve/main/mythomix-l2-13b.Q3_K_M.gguf"
            }
        },
        {
            "name": "mythomix-l2-13b.Q3_K_S.gguf",
            "size": "5658980224",
            "quantization": "Q3_K_S",
            "tags": [],
            "sha256": "a048d5bc8b8b2c60807e15dac7e2ca3389278430bc52391451e0b21405ad9c70",
            "download": {
                "default": "https://huggingface.co/TheBloke/MythoMix-L2-13B-GGUF/resolve/main/mythomix-l2-13b.Q3_K_S.gguf"
            }
        },
        {
            "name": "mythomix-l2-13b.Q4_0.gguf",
            "size": "7365834624",
            "quantization": "Q4_0",
            "tags": [],
            "sha256": "37a44d214737a83c96cdc7b73e8e9d28b9b1273475075085b7b4939210e21d70",
            "download": {
                "default": "https://huggingface.co/TheBloke/MythoMix-L2-13B-GGUF/resolve/main/mythomix-l2-13b.Q4_0.gguf"
            }
        },
        {
            "name": "mythomix-l2-13b.Q4_K_M.gguf",
            "size": "7865956224",
            "quantization": "Q4_K_M",
            "tags": [],
            "sha256": "d8c03e82b6d5c930ac64a756e7945056276714f76791a6d16caeff890fe50367",
            "download": {
                "default": "https://huggingface.co/TheBloke/MythoMix-L2-13B-GGUF/resolve/main/mythomix-l2-13b.Q4_K_M.gguf"
            }
        },
        {
            "name": "mythomix-l2-13b.Q4_K_S.gguf",
            "size": "7414331264",
            "quantization": "Q4_K_S",
            "tags": [],
            "sha256": "c4f4bc718bd87f1ac33c8b5cdea2cb394dbbc436fb033d00a7cf0d620285d02e",
            "download": {
                "default": "https://huggingface.co/TheBloke/MythoMix-L2-13B-GGUF/resolve/main/mythomix-l2-13b.Q4_K_S.gguf"
            }
        },
        {
            "name": "mythomix-l2-13b.Q5_0.gguf",
            "size": "8972285824",
            "quantization": "Q5_0",
            "tags": [],
            "sha256": "f9fecec500c84545c3e02f38fadd14d46c365f24c139351b215e6daef453f554",
            "download": {
                "default": "https://huggingface.co/TheBloke/MythoMix-L2-13B-GGUF/resolve/main/mythomix-l2-13b.Q5_0.gguf"
            }
        },
        {
            "name": "mythomix-l2-13b.Q5_K_M.gguf",
            "size": "9229924224",
            "quantization": "Q5_K_M",
            "tags": [],
            "sha256": "e94d9c0a24601e91a7f32ae837d6196031ce1888a8fd94208e2c9e8f9602307b",
            "download": {
                "default": "https://huggingface.co/TheBloke/MythoMix-L2-13B-GGUF/resolve/main/mythomix-l2-13b.Q5_K_M.gguf"
            }
        },
        {
            "name": "mythomix-l2-13b.Q5_K_S.gguf",
            "size": "8972285824",
            "quantization": "Q5_K_S",
            "tags": [],
            "sha256": "075e1d2227df15230c31699f4d9f2b4d9e2316f53c567111b68142f0d7dcd426",
            "download": {
                "default": "https://huggingface.co/TheBloke/MythoMix-L2-13B-GGUF/resolve/main/mythomix-l2-13b.Q5_K_S.gguf"
            }
        },
        {
            "name": "mythomix-l2-13b.Q6_K.gguf",
            "size": "10679140224",
            "quantization": "Q6_K",
            "tags": [],
            "sha256": "9a2a064858c9558a9615c95cf28c734d8e82e14900075691292a7314b47172f0",
            "download": {
                "default": "https://huggingface.co/TheBloke/MythoMix-L2-13B-GGUF/resolve/main/mythomix-l2-13b.Q6_K.gguf"
            }
        },
        {
            "name": "mythomix-l2-13b.Q8_0.gguf",
            "size": "13831319424",
            "quantization": "Q8_0",
            "tags": [],
            "sha256": "1d61e63674cef900c4d3188b0db7e546b5a4ca2a5927fef0907597b3df1751fe",
            "download": {
                "default": "https://huggingface.co/TheBloke/MythoMix-L2-13B-GGUF/resolve/main/mythomix-l2-13b.Q8_0.gguf"
            }
        }
    ],
    "prompt_template": "",
    "reverse_prompt": "",
    "context_size": 0,
    "vector_size": 0,
    "metrics": {}
}