{
    "id": "TheBloke/openchat-3.5-0106-GGUF",
    "status": "init",
    "model_type": "unknown",
    "name": "",
    "summary": "",
    "author": {
        "name": "TheBloke",
        "url": "https://github.com/TheBloke",
        "description": ""
    },
    "size": "",
    "requires": "",
    "released_at": "2024-01-10T10:49:16Z",
    "architecture": "",
    "files": [
        {
            "name": "openchat-3.5-0106.Q2_K.gguf",
            "size": "3083107552",
            "quantization": "Q2_K",
            "tags": [],
            "sha256": "5026252eb208f6272e836d86c3b52cf6714fb4b6b15a1e231e6fc7a72f51d2f6",
            "download": {
                "default": "https://huggingface.co/TheBloke/openchat-3.5-0106-GGUF/resolve/main/openchat-3.5-0106.Q2_K.gguf"
            }
        },
        {
            "name": "openchat-3.5-0106.Q3_K_L.gguf",
            "size": "3822034976",
            "quantization": "Q3_K_L",
            "tags": [],
            "sha256": "4236511c629283ffee2fe6a5d5daa5319cdc8494e97ff23a54a0896505e6d7d5",
            "download": {
                "default": "https://huggingface.co/TheBloke/openchat-3.5-0106-GGUF/resolve/main/openchat-3.5-0106.Q3_K_L.gguf"
            }
        },
        {
            "name": "openchat-3.5-0106.Q3_K_M.gguf",
            "size": "3518996512",
            "quantization": "Q3_K_M",
            "tags": [],
            "sha256": "9a1cdbe9da1fd44876cb7bc5aacf4b24212f2e962e15314354d843d75092de48",
            "download": {
                "default": "https://huggingface.co/TheBloke/openchat-3.5-0106-GGUF/resolve/main/openchat-3.5-0106.Q3_K_M.gguf"
            }
        },
        {
            "name": "openchat-3.5-0106.Q3_K_S.gguf",
            "size": "3164577824",
            "quantization": "Q3_K_S",
            "tags": [],
            "sha256": "e254ed6864efee4912695127a04c4892350092b03b5cf53db3adc8d091f8c058",
            "download": {
                "default": "https://huggingface.co/TheBloke/openchat-3.5-0106-GGUF/resolve/main/openchat-3.5-0106.Q3_K_S.gguf"
            }
        },
        {
            "name": "openchat-3.5-0106.Q4_0.gguf",
            "size": "4108928096",
            "quantization": "Q4_0",
            "tags": [],
            "sha256": "01e2e59616baab8ad941a2804cb47d6ef5a4fb81cb56f94707b0fc1a82d34bd7",
            "download": {
                "default": "https://huggingface.co/TheBloke/openchat-3.5-0106-GGUF/resolve/main/openchat-3.5-0106.Q4_0.gguf"
            }
        },
        {
            "name": "openchat-3.5-0106.Q4_K_M.gguf",
            "size": "4368450656",
            "quantization": "Q4_K_M",
            "tags": [],
            "sha256": "49190d4d039e6dea463e567ebce707eb001648f4ba01e43eb7fa88d9975fc0ce",
            "download": {
                "default": "https://huggingface.co/TheBloke/openchat-3.5-0106-GGUF/resolve/main/openchat-3.5-0106.Q4_K_M.gguf"
            }
        },
        {
            "name": "openchat-3.5-0106.Q4_K_S.gguf",
            "size": "4140385376",
            "quantization": "Q4_K_S",
            "tags": [],
            "sha256": "b72d156a77b7c492ba39e6033bf583649d888efcc91cc1769cebe7d72cb0d321",
            "download": {
                "default": "https://huggingface.co/TheBloke/openchat-3.5-0106-GGUF/resolve/main/openchat-3.5-0106.Q4_K_S.gguf"
            }
        },
        {
            "name": "openchat-3.5-0106.Q5_0.gguf",
            "size": "4997728352",
            "quantization": "Q5_0",
            "tags": [],
            "sha256": "9b9e2863982c8bb6e4ffa39519a7a383a869961ad3f207b1917a5960e7143b1d",
            "download": {
                "default": "https://huggingface.co/TheBloke/openchat-3.5-0106-GGUF/resolve/main/openchat-3.5-0106.Q5_0.gguf"
            }
        },
        {
            "name": "openchat-3.5-0106.Q5_K_M.gguf",
            "size": "5131421792",
            "quantization": "Q5_K_M",
            "tags": [],
            "sha256": "36a74fec42da7c3fc2614ce3444a99868647342ff4789f0e0d82882d7735aab5",
            "download": {
                "default": "https://huggingface.co/TheBloke/openchat-3.5-0106-GGUF/resolve/main/openchat-3.5-0106.Q5_K_M.gguf"
            }
        },
        {
            "name": "openchat-3.5-0106.Q5_K_S.gguf",
            "size": "4997728352",
            "quantization": "Q5_K_S",
            "tags": [],
            "sha256": "594eadb464ced905508f288d0c8c05b4e8ad62208a6718381ebe1b29f3a5f611",
            "download": {
                "default": "https://huggingface.co/TheBloke/openchat-3.5-0106-GGUF/resolve/main/openchat-3.5-0106.Q5_K_S.gguf"
            }
        },
        {
            "name": "openchat-3.5-0106.Q6_K.gguf",
            "size": "5942078624",
            "quantization": "Q6_K",
            "tags": [],
            "sha256": "11ffb503fcdbf4a6512786a139102ec7f0665a669b80a1575bfe38719f02e913",
            "download": {
                "default": "https://huggingface.co/TheBloke/openchat-3.5-0106-GGUF/resolve/main/openchat-3.5-0106.Q6_K.gguf"
            }
        },
        {
            "name": "openchat-3.5-0106.Q8_0.gguf",
            "size": "7695875104",
            "quantization": "Q8_0",
            "tags": [],
            "sha256": "69ef6975cce795b5b433e23577eb8d38421fe7064d73ef91d3f323409d2696fb",
            "download": {
                "default": "https://huggingface.co/TheBloke/openchat-3.5-0106-GGUF/resolve/main/openchat-3.5-0106.Q8_0.gguf"
            }
        }
    ],
    "prompt_template": "",
    "reverse_prompt": "",
    "context_size": 0,
    "vector_size": 0,
    "metrics": {}
}