{
    "id": "masonym/gigabyte-faq-7B-q4_0-GGUF",
    "status": "init",
    "model_type": "unknown",
    "name": "",
    "summary": "",
    "author": {
        "name": "masonym",
        "url": "",
        "description": ""
    },
    "size": "",
    "requires": "",
    "released_at": "2023-12-08T01:16:01Z",
    "architecture": "",
    "files": [
        {
            "name": "gigabyte-faq-7B-q4_0.gguf",
            "size": "3825812896",
            "quantization": "",
            "tags": [],
            "sha256": "3bbe763cfc729604401ed738a442806eb4924f181c360a939bae5c293b3d5cb1",
            "download": {
                "default": "https://huggingface.co/masonym/gigabyte-faq-7B-q4_0-GGUF/resolve/main/gigabyte-faq-7B-q4_0.gguf"
            }
        }
    ],
    "prompt_template": "",
    "reverse_prompt": "",
    "context_size": 0,
    "vector_size": 0,
    "metrics": {}
}