{
    "id": "qwp4w3hyb/Cerebrum-1.0-8x7b-GGUF",
    "status": "init",
    "model_type": "unknown",
    "name": "",
    "summary": "",
    "author": {
        "name": "qwp4w3hyb",
        "url": "",
        "description": ""
    },
    "size": "",
    "requires": "",
    "released_at": "2024-03-20T12:13:05Z",
    "architecture": "",
    "files": [
        {
            "name": "cerebrum-1.0-8x7b-Q2_K.gguf",
            "size": "17309174304",
            "quantization": "Q2_K",
            "tags": [],
            "sha256": "2ec92b04fc6a105d8956ee37e26a84a24c2ed90adce6aae9cd2cc53e90a8de4c",
            "download": {
                "default": "https://huggingface.co/qwp4w3hyb/Cerebrum-1.0-8x7b-GGUF/resolve/main/cerebrum-1.0-8x7b-Q2_K.gguf"
            }
        },
        {
            "name": "cerebrum-1.0-8x7b-Q3_K_M.gguf",
            "size": "22544394784",
            "quantization": "Q3_K_M",
            "tags": [],
            "sha256": "2acafdca90350fb7876ac3098c05b2faaa38cdbeee6906ee0a0db7233c7b1a9a",
            "download": {
                "default": "https://huggingface.co/qwp4w3hyb/Cerebrum-1.0-8x7b-GGUF/resolve/main/cerebrum-1.0-8x7b-Q3_K_M.gguf"
            }
        },
        {
            "name": "cerebrum-1.0-8x7b-Q4_K_M.gguf",
            "size": "28446411296",
            "quantization": "Q4_K_M",
            "tags": [],
            "sha256": "8097240da4aa16e14209c164edf01cbfcbb6adede194c47f5e3299a44995e871",
            "download": {
                "default": "https://huggingface.co/qwp4w3hyb/Cerebrum-1.0-8x7b-GGUF/resolve/main/cerebrum-1.0-8x7b-Q4_K_M.gguf"
            }
        },
        {
            "name": "cerebrum-1.0-8x7b-Q5_K_S.gguf",
            "size": "32229280288",
            "quantization": "Q5_K_S",
            "tags": [],
            "sha256": "bf16a98932d0caf5d4c7c5abb63b4d38d0558dc5453d540ee5de5ccaba7e98d7",
            "download": {
                "default": "https://huggingface.co/qwp4w3hyb/Cerebrum-1.0-8x7b-GGUF/resolve/main/cerebrum-1.0-8x7b-Q5_K_S.gguf"
            }
        },
        {
            "name": "cerebrum-1.0-8x7b-Q6_K.gguf",
            "size": "38378760736",
            "quantization": "Q6_K",
            "tags": [],
            "sha256": "0b407c6f887a0a40d0ed1d9d4ebd8fdb6cdcb04c3394aeb46b02cb068761589c",
            "download": {
                "default": "https://huggingface.co/qwp4w3hyb/Cerebrum-1.0-8x7b-GGUF/resolve/main/cerebrum-1.0-8x7b-Q6_K.gguf"
            }
        }
    ],
    "prompt_template": "",
    "reverse_prompt": "",
    "context_size": 0,
    "vector_size": 0,
    "metrics": {}
}