{
    "id": "ddh0/openchat_3.5-GGUF-fp16",
    "status": "init",
    "model_type": "unknown",
    "name": "",
    "summary": "",
    "author": {
        "name": "ddh0",
        "url": "",
        "description": ""
    },
    "size": "",
    "requires": "",
    "released_at": "2023-11-11T22:22:33Z",
    "architecture": "",
    "files": [
        {
            "name": "openchat_3.5-fp16.gguf",
            "size": "14484764384",
            "quantization": "",
            "tags": [],
            "sha256": "f273a65093fb01d291f9e8b574d430938bda691097873b0c0d9d20a5db1741b7",
            "download": {
                "default": "https://huggingface.co/ddh0/openchat_3.5-GGUF-fp16/resolve/main/openchat_3.5-fp16.gguf"
            }
        }
    ],
    "prompt_template": "",
    "reverse_prompt": "",
    "context_size": 0,
    "vector_size": 0,
    "metrics": {}
}