{
    "id": "NeverSleep/Mistral-11B-SynthIAirOmniMix-GGUF",
    "status": "init",
    "model_type": "unknown",
    "name": "",
    "summary": "",
    "author": {
        "name": "NeverSleep",
        "url": "",
        "description": ""
    },
    "size": "",
    "requires": "",
    "released_at": "2023-10-14T15:23:48Z",
    "architecture": "",
    "files": [
        {
            "name": "Mistral-11B-SynthIAirOmniMix.q4_k_m.gguf",
            "size": "6461667360",
            "quantization": "",
            "tags": [],
            "sha256": "25e3af1b95d336f648f727fc18ca7e63bec6dc5cc07f19fd18de468281d95cc8",
            "download": {
                "default": "https://huggingface.co/NeverSleep/Mistral-11B-SynthIAirOmniMix-GGUF/resolve/main/Mistral-11B-SynthIAirOmniMix.q4_k_m.gguf"
            }
        },
        {
            "name": "Mistral-11B-SynthIAirOmniMix.q5_k_m.gguf",
            "size": "7597930528",
            "quantization": "",
            "tags": [],
            "sha256": "ed76e17da35f7697fc32b9e052ce5c6dae5e0a3ca467d51fa08e9b5e7423a623",
            "download": {
                "default": "https://huggingface.co/NeverSleep/Mistral-11B-SynthIAirOmniMix-GGUF/resolve/main/Mistral-11B-SynthIAirOmniMix.q5_k_m.gguf"
            }
        },
        {
            "name": "Mistral-11B-SynthIAirOmniMix.q6_k.gguf",
            "size": "8805210144",
            "quantization": "",
            "tags": [],
            "sha256": "3368de11bbe376b98b3a70b0ab80034049ce7929f4b55e48ef29f2d9f1092670",
            "download": {
                "default": "https://huggingface.co/NeverSleep/Mistral-11B-SynthIAirOmniMix-GGUF/resolve/main/Mistral-11B-SynthIAirOmniMix.q6_k.gguf"
            }
        },
        {
            "name": "Mistral-11B-SynthIAirOmniMix.q8_0.gguf",
            "size": "11404154912",
            "quantization": "",
            "tags": [],
            "sha256": "c114ab1f35480b763bda7e927ef65ca38b2bd6fdef7309aa832f1d6ff2149d2d",
            "download": {
                "default": "https://huggingface.co/NeverSleep/Mistral-11B-SynthIAirOmniMix-GGUF/resolve/main/Mistral-11B-SynthIAirOmniMix.q8_0.gguf"
            }
        }
    ],
    "prompt_template": "",
    "reverse_prompt": "",
    "context_size": 0,
    "vector_size": 0,
    "metrics": {}
}