{
    "id": "jartine/TinyLlama-1.1B-Chat-v1.0-GGUF",
    "status": "init",
    "model_type": "unknown",
    "name": "",
    "summary": "",
    "author": {
        "name": "jartine",
        "url": "",
        "description": ""
    },
    "size": "",
    "requires": "",
    "released_at": "2024-01-01T11:29:06Z",
    "architecture": "",
    "files": [
        {
            "name": "TinyLlama-1.1B-Chat-v1.0.f16.gguf",
            "size": "",
            "quantization": "",
            "tags": [],
            "sha256": "",
            "download": {
                "default": "https://huggingface.co/jartine/TinyLlama-1.1B-Chat-v1.0-GGUF/resolve/main/TinyLlama-1.1B-Chat-v1.0.f16.gguf"
            }
        },
        {
            "name": "TinyLlama-1.1B-Chat-v1.0.Q2_K.gguf",
            "size": "",
            "quantization": "",
            "tags": [],
            "sha256": "",
            "download": {
                "default": "https://huggingface.co/jartine/TinyLlama-1.1B-Chat-v1.0-GGUF/resolve/main/TinyLlama-1.1B-Chat-v1.0.Q2_K.gguf"
            }
        },
        {
            "name": "TinyLlama-1.1B-Chat-v1.0.Q3_K_L.gguf",
            "size": "",
            "quantization": "",
            "tags": [],
            "sha256": "",
            "download": {
                "default": "https://huggingface.co/jartine/TinyLlama-1.1B-Chat-v1.0-GGUF/resolve/main/TinyLlama-1.1B-Chat-v1.0.Q3_K_L.gguf"
            }
        },
        {
            "name": "TinyLlama-1.1B-Chat-v1.0.Q3_K_M.gguf",
            "size": "",
            "quantization": "",
            "tags": [],
            "sha256": "",
            "download": {
                "default": "https://huggingface.co/jartine/TinyLlama-1.1B-Chat-v1.0-GGUF/resolve/main/TinyLlama-1.1B-Chat-v1.0.Q3_K_M.gguf"
            }
        },
        {
            "name": "TinyLlama-1.1B-Chat-v1.0.Q3_K_S.gguf",
            "size": "",
            "quantization": "",
            "tags": [],
            "sha256": "",
            "download": {
                "default": "https://huggingface.co/jartine/TinyLlama-1.1B-Chat-v1.0-GGUF/resolve/main/TinyLlama-1.1B-Chat-v1.0.Q3_K_S.gguf"
            }
        },
        {
            "name": "TinyLlama-1.1B-Chat-v1.0.Q4_0.gguf",
            "size": "",
            "quantization": "",
            "tags": [],
            "sha256": "",
            "download": {
                "default": "https://huggingface.co/jartine/TinyLlama-1.1B-Chat-v1.0-GGUF/resolve/main/TinyLlama-1.1B-Chat-v1.0.Q4_0.gguf"
            }
        },
        {
            "name": "TinyLlama-1.1B-Chat-v1.0.Q4_K_M.gguf",
            "size": "",
            "quantization": "",
            "tags": [],
            "sha256": "",
            "download": {
                "default": "https://huggingface.co/jartine/TinyLlama-1.1B-Chat-v1.0-GGUF/resolve/main/TinyLlama-1.1B-Chat-v1.0.Q4_K_M.gguf"
            }
        },
        {
            "name": "TinyLlama-1.1B-Chat-v1.0.Q4_K_S.gguf",
            "size": "",
            "quantization": "",
            "tags": [],
            "sha256": "",
            "download": {
                "default": "https://huggingface.co/jartine/TinyLlama-1.1B-Chat-v1.0-GGUF/resolve/main/TinyLlama-1.1B-Chat-v1.0.Q4_K_S.gguf"
            }
        },
        {
            "name": "TinyLlama-1.1B-Chat-v1.0.Q5_0.gguf",
            "size": "",
            "quantization": "",
            "tags": [],
            "sha256": "",
            "download": {
                "default": "https://huggingface.co/jartine/TinyLlama-1.1B-Chat-v1.0-GGUF/resolve/main/TinyLlama-1.1B-Chat-v1.0.Q5_0.gguf"
            }
        },
        {
            "name": "TinyLlama-1.1B-Chat-v1.0.Q5_K_M.gguf",
            "size": "",
            "quantization": "",
            "tags": [],
            "sha256": "",
            "download": {
                "default": "https://huggingface.co/jartine/TinyLlama-1.1B-Chat-v1.0-GGUF/resolve/main/TinyLlama-1.1B-Chat-v1.0.Q5_K_M.gguf"
            }
        },
        {
            "name": "TinyLlama-1.1B-Chat-v1.0.Q5_K_S.gguf",
            "size": "",
            "quantization": "",
            "tags": [],
            "sha256": "",
            "download": {
                "default": "https://huggingface.co/jartine/TinyLlama-1.1B-Chat-v1.0-GGUF/resolve/main/TinyLlama-1.1B-Chat-v1.0.Q5_K_S.gguf"
            }
        },
        {
            "name": "TinyLlama-1.1B-Chat-v1.0.Q6_K.gguf",
            "size": "",
            "quantization": "",
            "tags": [],
            "sha256": "",
            "download": {
                "default": "https://huggingface.co/jartine/TinyLlama-1.1B-Chat-v1.0-GGUF/resolve/main/TinyLlama-1.1B-Chat-v1.0.Q6_K.gguf"
            }
        },
        {
            "name": "TinyLlama-1.1B-Chat-v1.0.Q8_0.gguf",
            "size": "",
            "quantization": "",
            "tags": [],
            "sha256": "",
            "download": {
                "default": "https://huggingface.co/jartine/TinyLlama-1.1B-Chat-v1.0-GGUF/resolve/main/TinyLlama-1.1B-Chat-v1.0.Q8_0.gguf"
            }
        }
    ],
    "prompt_template": "",
    "reverse_prompt": "",
    "context_size": 0,
    "vector_size": 0,
    "metrics": {}
}