{
    "id": "l3utterfly/tinyllama-1.1b-layla-v4-gguf",
    "status": "init",
    "model_type": "unknown",
    "name": "",
    "summary": "",
    "author": {
        "name": "l3utterfly",
        "url": "",
        "description": ""
    },
    "size": "",
    "requires": "",
    "released_at": "2024-04-01T03:40:59Z",
    "architecture": "",
    "files": [
        {
            "name": "tinyllama-1.1b-layla-v4-f32.gguf",
            "size": "4400929280",
            "quantization": "",
            "tags": [],
            "sha256": "79f1a7f8993e1e342292c97eef293bc0ce9faa4ef2a27f5014f80272ce8a1545",
            "download": {
                "default": "https://huggingface.co/l3utterfly/tinyllama-1.1b-layla-v4-gguf/resolve/main/tinyllama-1.1b-layla-v4-f32.gguf"
            }
        },
        {
            "name": "tinyllama-1.1b-layla-v4-Q4_K.gguf",
            "size": "667814432",
            "quantization": "Q4_K",
            "tags": [],
            "sha256": "a24cc8b24d7f310486da844fbf0f7a6c3c115d7c08061d0d49a79ef63c2dbe76",
            "download": {
                "default": "https://huggingface.co/l3utterfly/tinyllama-1.1b-layla-v4-gguf/resolve/main/tinyllama-1.1b-layla-v4-Q4_K.gguf"
            }
        }
    ],
    "prompt_template": "",
    "reverse_prompt": "",
    "context_size": 0,
    "vector_size": 0,
    "metrics": null
}