{
    "id": "mradermacher/Dicephal-123B-i1-GGUF",
    "status": "init",
    "model_type": "unknown",
    "name": "",
    "summary": "",
    "author": {
        "name": "mradermacher",
        "url": "",
        "description": ""
    },
    "size": "",
    "requires": "",
    "released_at": "2024-03-21T17:08:07Z",
    "architecture": "",
    "files": [
        {
            "name": "Dicephal-123B.i1-IQ1_S.gguf",
            "size": "26294434880",
            "quantization": "Q1_S",
            "tags": [],
            "sha256": "8a5431cd47d8d0693243473162bb07fbd7ff1efa1133db71f32c4032a08b2f44",
            "download": {
                "default": "https://huggingface.co/mradermacher/Dicephal-123B-i1-GGUF/resolve/main/Dicephal-123B.i1-IQ1_S.gguf"
            }
        },
        {
            "name": "Dicephal-123B.i1-IQ2_M.gguf",
            "size": "41925442624",
            "quantization": "Q2_M",
            "tags": [],
            "sha256": "904aa3b93e544476be78ee7965ae69618a63fc22fa04ed6fec04903183910d43",
            "download": {
                "default": "https://huggingface.co/mradermacher/Dicephal-123B-i1-GGUF/resolve/main/Dicephal-123B.i1-IQ2_M.gguf"
            }
        },
        {
            "name": "Dicephal-123B.i1-IQ2_S.gguf",
            "size": "38546930752",
            "quantization": "Q2_S",
            "tags": [],
            "sha256": "97643e65edac1f12b66d765311f2dd613d642386898b4f741a82dea9f9472a4d",
            "download": {
                "default": "https://huggingface.co/mradermacher/Dicephal-123B-i1-GGUF/resolve/main/Dicephal-123B.i1-IQ2_S.gguf"
            }
        },
        {
            "name": "Dicephal-123B.i1-IQ2_XS.gguf",
            "size": "36731960384",
            "quantization": "Q2_XS",
            "tags": [],
            "sha256": "9d5a3e4c9045c4a9d3f8275bff776bce9c3940a9c1ea4d43803af89d1e26c2ca",
            "download": {
                "default": "https://huggingface.co/mradermacher/Dicephal-123B-i1-GGUF/resolve/main/Dicephal-123B.i1-IQ2_XS.gguf"
            }
        },
        {
            "name": "Dicephal-123B.i1-IQ2_XXS.gguf",
            "size": "33051458624",
            "quantization": "Q2_XXS",
            "tags": [],
            "sha256": "8a966ec1be079a472150158a11a35580f68792e12b1b08c4adf13e07e1bd5f1a",
            "download": {
                "default": "https://huggingface.co/mradermacher/Dicephal-123B-i1-GGUF/resolve/main/Dicephal-123B.i1-IQ2_XXS.gguf"
            }
        },
        {
            "name": "Dicephal-123B.i1-IQ3_XXS.gguf",
            "size": "47804808256",
            "quantization": "Q3_XXS",
            "tags": [],
            "sha256": "ca816dff6510dc6ebdaa47be235cdf6ffacd00037a8ec32c8dae36de92801323",
            "download": {
                "default": "https://huggingface.co/mradermacher/Dicephal-123B-i1-GGUF/resolve/main/Dicephal-123B.i1-IQ3_XXS.gguf"
            }
        },
        {
            "name": "Dicephal-123B.i1-Q2_K.gguf",
            "size": "45749189696",
            "quantization": "Q2_K",
            "tags": [],
            "sha256": "b6c45d30294aeaccb27e81c2a355608d360e04dc881f62c84c7436b8780ddf96",
            "download": {
                "default": "https://huggingface.co/mradermacher/Dicephal-123B-i1-GGUF/resolve/main/Dicephal-123B.i1-Q2_K.gguf"
            }
        }
    ],
    "prompt_template": "",
    "reverse_prompt": "",
    "context_size": 0,
    "vector_size": 0,
    "metrics": {}
}