{
    "id": "mradermacher/StarFuse-7B-DARE-GGUF",
    "status": "init",
    "model_type": "unknown",
    "name": "",
    "summary": "",
    "author": {
        "name": "mradermacher",
        "url": "",
        "description": ""
    },
    "size": "",
    "requires": "",
    "released_at": "2024-03-30T10:06:48Z",
    "architecture": "",
    "files": [
        {
            "name": "StarFuse-7B-DARE.IQ3_M.gguf",
            "size": "3439535552",
            "quantization": "Q3_M",
            "tags": [],
            "sha256": "efd520f1d0849439d50e9fe952e24bf22cef0ffde2cbf82a36a5524eb87665bf",
            "download": {
                "default": "https://huggingface.co/mradermacher/StarFuse-7B-DARE-GGUF/resolve/main/StarFuse-7B-DARE.IQ3_M.gguf"
            }
        },
        {
            "name": "StarFuse-7B-DARE.IQ3_S.gguf",
            "size": "3337037248",
            "quantization": "Q3_S",
            "tags": [],
            "sha256": "2213e7735f82e1f79cda21ac4773ae7cbff13fa4654093bb67b67ad52934c816",
            "download": {
                "default": "https://huggingface.co/mradermacher/StarFuse-7B-DARE-GGUF/resolve/main/StarFuse-7B-DARE.IQ3_S.gguf"
            }
        },
        {
            "name": "StarFuse-7B-DARE.IQ3_XS.gguf",
            "size": "3173459392",
            "quantization": "Q3_XS",
            "tags": [],
            "sha256": "6b164cbe49fc97ac8998c76541d2d7670ce345e567adf9e375b5bcad8f2da331",
            "download": {
                "default": "https://huggingface.co/mradermacher/StarFuse-7B-DARE-GGUF/resolve/main/StarFuse-7B-DARE.IQ3_XS.gguf"
            }
        },
        {
            "name": "StarFuse-7B-DARE.IQ4_NL.gguf",
            "size": "4309699072",
            "quantization": "Q4_NL",
            "tags": [],
            "sha256": "4c012de1ad903a1d50385c688355df44efd1e9439ab9f88dc229941220b1c713",
            "download": {
                "default": "https://huggingface.co/mradermacher/StarFuse-7B-DARE-GGUF/resolve/main/StarFuse-7B-DARE.IQ4_NL.gguf"
            }
        },
        {
            "name": "StarFuse-7B-DARE.IQ4_XS.gguf",
            "size": "4099033344",
            "quantization": "Q4_XS",
            "tags": [],
            "sha256": "af9c094d050053743a887d1a3809d465251f898e9e01186635b97d4892457f89",
            "download": {
                "default": "https://huggingface.co/mradermacher/StarFuse-7B-DARE-GGUF/resolve/main/StarFuse-7B-DARE.IQ4_XS.gguf"
            }
        },
        {
            "name": "StarFuse-7B-DARE.Q2_K.gguf",
            "size": "2873885312",
            "quantization": "Q2_K",
            "tags": [],
            "sha256": "5b62e5499fe0580d1566406ffbbe7ac03197a67eaa4e31b6c72a2a33aa82ee41",
            "download": {
                "default": "https://huggingface.co/mradermacher/StarFuse-7B-DARE-GGUF/resolve/main/StarFuse-7B-DARE.Q2_K.gguf"
            }
        },
        {
            "name": "StarFuse-7B-DARE.Q3_K_L.gguf",
            "size": "3976668608",
            "quantization": "Q3_K_L",
            "tags": [],
            "sha256": "ff049ffeaab45c0ddd4ababc170cc501d75987534606e4225f36cd1063b555fb",
            "download": {
                "default": "https://huggingface.co/mradermacher/StarFuse-7B-DARE-GGUF/resolve/main/StarFuse-7B-DARE.Q3_K_L.gguf"
            }
        },
        {
            "name": "StarFuse-7B-DARE.Q3_K_M.gguf",
            "size": "3673630144",
            "quantization": "Q3_K_M",
            "tags": [],
            "sha256": "42c0d6665e134fed9a0ea473d3308ea9110563ef1454d3b43d7c95c2e040bf3b",
            "download": {
                "default": "https://huggingface.co/mradermacher/StarFuse-7B-DARE-GGUF/resolve/main/StarFuse-7B-DARE.Q3_K_M.gguf"
            }
        },
        {
            "name": "StarFuse-7B-DARE.Q3_K_S.gguf",
            "size": "3319211456",
            "quantization": "Q3_K_S",
            "tags": [],
            "sha256": "cda948bcccd4025829c769699b54abad27ea7df99ee2325547ec6f56e4b0a320",
            "download": {
                "default": "https://huggingface.co/mradermacher/StarFuse-7B-DARE-GGUF/resolve/main/StarFuse-7B-DARE.Q3_K_S.gguf"
            }
        },
        {
            "name": "StarFuse-7B-DARE.Q4_0.gguf",
            "size": "4263561728",
            "quantization": "Q4_0",
            "tags": [],
            "sha256": "ed671f4a6a54b13da921fabac28829fc9488c0add679e77acf6d5a1a58ce93d4",
            "download": {
                "default": "https://huggingface.co/mradermacher/StarFuse-7B-DARE-GGUF/resolve/main/StarFuse-7B-DARE.Q4_0.gguf"
            }
        },
        {
            "name": "StarFuse-7B-DARE.Q4_K_M.gguf",
            "size": "4523084288",
            "quantization": "Q4_K_M",
            "tags": [],
            "sha256": "eb40adfdd8e25c37b40be1c7a9c36c42b520e2b88acec266028331f7d84a6d5b",
            "download": {
                "default": "https://huggingface.co/mradermacher/StarFuse-7B-DARE-GGUF/resolve/main/StarFuse-7B-DARE.Q4_K_M.gguf"
            }
        },
        {
            "name": "StarFuse-7B-DARE.Q4_K_S.gguf",
            "size": "4295019008",
            "quantization": "Q4_K_S",
            "tags": [],
            "sha256": "0f0512a2d7e8c2a0e3ce088d61376ca6ed50766d60455e475bedd2b67e4d5d12",
            "download": {
                "default": "https://huggingface.co/mradermacher/StarFuse-7B-DARE-GGUF/resolve/main/StarFuse-7B-DARE.Q4_K_S.gguf"
            }
        },
        {
            "name": "StarFuse-7B-DARE.Q5_K_M.gguf",
            "size": "5286055424",
            "quantization": "Q5_K_M",
            "tags": [],
            "sha256": "389a549bccfd851ef8d2c0810e4462d58d6a48c7ab811801a1b0d79ffd9e9f6f",
            "download": {
                "default": "https://huggingface.co/mradermacher/StarFuse-7B-DARE-GGUF/resolve/main/StarFuse-7B-DARE.Q5_K_M.gguf"
            }
        },
        {
            "name": "StarFuse-7B-DARE.Q5_K_S.gguf",
            "size": "5152361984",
            "quantization": "Q5_K_S",
            "tags": [],
            "sha256": "7abd11793d24a4021561ab4e730f4b74df6b83d49de74bfe11b8ea4395491aa0",
            "download": {
                "default": "https://huggingface.co/mradermacher/StarFuse-7B-DARE-GGUF/resolve/main/StarFuse-7B-DARE.Q5_K_S.gguf"
            }
        },
        {
            "name": "StarFuse-7B-DARE.Q6_K.gguf",
            "size": "6096712256",
            "quantization": "Q6_K",
            "tags": [],
            "sha256": "088ad1339d4d3ad99e8004c06b6d5c571730dd5a4a7fe558bf82d2231f431f0a",
            "download": {
                "default": "https://huggingface.co/mradermacher/StarFuse-7B-DARE-GGUF/resolve/main/StarFuse-7B-DARE.Q6_K.gguf"
            }
        },
        {
            "name": "StarFuse-7B-DARE.Q8_0.gguf",
            "size": "7818762752",
            "quantization": "Q8_0",
            "tags": [],
            "sha256": "be574c187aa2e62c13a08878bbae541bd3f16dc6b4321ea4d66ea68ff210e5b9",
            "download": {
                "default": "https://huggingface.co/mradermacher/StarFuse-7B-DARE-GGUF/resolve/main/StarFuse-7B-DARE.Q8_0.gguf"
            }
        }
    ],
    "prompt_template": "",
    "reverse_prompt": "",
    "context_size": 0,
    "vector_size": 0,
    "metrics": {}
}