{
    "id": "eriksu/heiko-7b-v0.4.gguf",
    "status": "init",
    "model_type": "unknown",
    "name": "",
    "summary": "",
    "author": {
        "name": "eriksu",
        "url": "",
        "description": ""
    },
    "size": "",
    "requires": "",
    "released_at": "2024-03-04T14:16:12Z",
    "architecture": "",
    "files": [
        {
            "name": "Heiko-7b-v0.4.gguf",
            "size": "7695857344",
            "quantization": "",
            "tags": [],
            "sha256": "17760d01539cba9ea8f58501879a0b15279b5c2ba1c2a09583e7e6c2534d182b",
            "download": {
                "default": "https://huggingface.co/eriksu/heiko-7b-v0.4.gguf/resolve/main/Heiko-7b-v0.4.gguf"
            }
        }
    ],
    "prompt_template": "",
    "reverse_prompt": "",
    "context_size": 0,
    "vector_size": 0,
    "metrics": {}
}