{
    "id": "LoneStriker/Einstein-v4-7B-GGUF",
    "status": "init",
    "model_type": "unknown",
    "name": "",
    "summary": "",
    "author": {
        "name": "LoneStriker",
        "url": "",
        "description": ""
    },
    "size": "",
    "requires": "",
    "released_at": "2024-03-02T18:42:10Z",
    "architecture": "",
    "files": [
        {
            "name": "Einstein-v4-7B-Q3_K_L.gguf",
            "size": "3822035328",
            "quantization": "Q3_K_L",
            "tags": [],
            "sha256": "7d7954f284d36017031fe27fcf31f0de2cdf50a7ed020e1239441186bca722e7",
            "download": {
                "default": "https://huggingface.co/LoneStriker/Einstein-v4-7B-GGUF/resolve/main/Einstein-v4-7B-Q3_K_L.gguf"
            }
        },
        {
            "name": "Einstein-v4-7B-Q4_K_M.gguf",
            "size": "4368451008",
            "quantization": "Q4_K_M",
            "tags": [],
            "sha256": "eb68812fd71d179d178b03f58d4e2b8544e160a19dbbe1e3ee7b01e8270224ba",
            "download": {
                "default": "https://huggingface.co/LoneStriker/Einstein-v4-7B-GGUF/resolve/main/Einstein-v4-7B-Q4_K_M.gguf"
            }
        },
        {
            "name": "Einstein-v4-7B-Q5_K_M.gguf",
            "size": "5131422144",
            "quantization": "Q5_K_M",
            "tags": [],
            "sha256": "e3fa6a0047c0496569ccedea8dfc8eb87d69dfdef1b022f7ebd3362d4b436068",
            "download": {
                "default": "https://huggingface.co/LoneStriker/Einstein-v4-7B-GGUF/resolve/main/Einstein-v4-7B-Q5_K_M.gguf"
            }
        },
        {
            "name": "Einstein-v4-7B-Q6_K.gguf",
            "size": "5942078976",
            "quantization": "Q6_K",
            "tags": [],
            "sha256": "61f99baea2ca2e74a6d8e7e1400d9713363072aec05b85ec68f6b0d12a346ef1",
            "download": {
                "default": "https://huggingface.co/LoneStriker/Einstein-v4-7B-GGUF/resolve/main/Einstein-v4-7B-Q6_K.gguf"
            }
        },
        {
            "name": "Einstein-v4-7B-Q8_0.gguf",
            "size": "7695875456",
            "quantization": "Q8_0",
            "tags": [],
            "sha256": "c21f514d02de372561f3d28a563e819bac020e323c31a29395800adf82f6b3ff",
            "download": {
                "default": "https://huggingface.co/LoneStriker/Einstein-v4-7B-GGUF/resolve/main/Einstein-v4-7B-Q8_0.gguf"
            }
        }
    ],
    "prompt_template": "",
    "reverse_prompt": "",
    "context_size": 0,
    "vector_size": 0,
    "metrics": {}
}